services/__init__.py
services/setup.py
services/lib/__init__.py
services/lib/service.py
services/lib/test_validators.py
services/lib/tests.py
services/lib/repository/__init__.py
services/lib/repository/generics.py
services/lib/repository/models.py
services/lib/repository/tools.py
services/lib/repository/types.py
cpaDataServices-0.0.3.dist-info/METADATA
cpaDataServices-0.0.3.dist-info/WHEEL
cpaDataServices-0.0.3.dist-info/top_level.txt
cpaDataServices-0.0.3.dist-info/RECORD
